django_encrypted_id-0.3.2.dist-info/METADATA
django_encrypted_id-0.3.2.dist-info/RECORD
django_encrypted_id-0.3.2.dist-info/WHEEL
django_encrypted_id-0.3.2.dist-info/top_level.txt
django_encrypted_id-0.3.2.dist-info/zip-safe
encrypted_id/__init__.py
encrypted_id/models.py
